example_package_jdroldan/__init__.py
example_package_jdroldan/example.py
example_package_jdroldan-2.0.0.dist-info/LICENSE
example_package_jdroldan-2.0.0.dist-info/METADATA
example_package_jdroldan-2.0.0.dist-info/WHEEL
example_package_jdroldan-2.0.0.dist-info/top_level.txt
example_package_jdroldan-2.0.0.dist-info/RECORD
